{
    "id": "alcremie-ruby-swirl-love",
    "nid": "0869-ruby-swirl-love",
    "dexNum": 869,
    "formId": "ruby-swirl-love",
    "name": "Alcremie (Ruby Swirl Love)",
    "formName": "Ruby Swirl Love",
    "region": "galar",
    "generation": 8,
    "type1": "fairy",
    "type2": null,
    "color": "white",
    "abilities": {
        "primary": null,
        "secondary": null,
        "hidden": null
    },
    "isLegendary": false,
    "isMythical": false,
    "isUltraBeast": false,
    "ultraBeastCode": null,
    "isDefault": false,
    "isForm": true,
    "isSpecialAbilityForm": false,
    "isCosmeticForm": true,
    "isFemaleForm": false,
    "hasGenderDifferences": false,
    "isBattleOnlyForm": false,
    "isSwitchableForm": false,
    "isFusion": false,
    "fusedWith": null,
    "isMega": false,
    "isPrimal": false,
    "isRegional": false,
    "isGmax": false,
    "canGmax": false,
    "canDynamax": true,
    "canBeAlpha": false,
    "debutIn": "swsh",
    "obtainableIn": [
        "swsh"
    ],
    "versionExclusiveIn": [],
    "onlyViaEventIn": [],
    "storableIn": [
        "home",
        "swsh"
    ],
    "shinyReleased": true,
    "shinyBase": null,
    "baseStats": {
        "hp": -1,
        "atk": -1,
        "def": -1,
        "spa": -1,
        "spd": -1,
        "spe": -1
    },
    "goStats": {
        "maxCP": -1,
        "attack": -1,
        "defense": -1,
        "stamina": -1
    },
    "weight": {
        "avg": "-1kg",
        "min": "-1kg",
        "max": "-1kg",
        "alpha": "-1kg"
    },
    "height": {
        "avg": "-1m",
        "min": "-1m",
        "max": "-1m",
        "alpha": "-1m"
    },
    "maleRate": -1,
    "femaleRate": -1,
    "refs": {
        "pogo": "ALCREMIE_RUBY_SWIRL_LOVE",
        "veekunDb": "alcremie-ruby-swirl-love",
        "serebii": "alcremie",
        "bulbapedia": "Alcremie",
        "homeSprite": "alcremie-ruby-swirl-love",
        "miniSprite": "alcremie-ruby-swirl-love",
        "showdown": "alcremierubyswirllove",
        "showdownDef": "Alcremie-Ruby-Swirl-Love",
        "smogon": "alcremie-ruby-swirl-love"
    },
    "baseSpecies": "alcremie",
    "baseForms": [],
    "forms": null,
    "evolutions": []
}
