{
    "id": "articuno",
    "nid": "0144",
    "dexNum": 144,
    "formId": null,
    "name": "Articuno",
    "formName": null,
    "region": "kanto",
    "generation": 1,
    "type1": "ice",
    "type2": "flying",
    "color": "blue",
    "abilities": {
        "primary": "Pressure",
        "secondary": null,
        "hidden": "Snow Cloak"
    },
    "isLegendary": true,
    "isMythical": false,
    "isUltraBeast": false,
    "ultraBeastCode": null,
    "isDefault": true,
    "isForm": false,
    "isSpecialAbilityForm": false,
    "isCosmeticForm": false,
    "isFemaleForm": false,
    "hasGenderDifferences": false,
    "isBattleOnlyForm": false,
    "isSwitchableForm": false,
    "isFusion": false,
    "fusedWith": null,
    "isMega": false,
    "isPrimal": false,
    "isRegional": false,
    "isGmax": false,
    "canGmax": false,
    "canDynamax": true,
    "canBeAlpha": false,
    "debutIn": "rb",
    "obtainableIn": [
        "bdsp",
        "frlg",
        "go",
        "lgpe",
        "rb",
        "swsh",
        "y"
    ],
    "versionExclusiveIn": [],
    "eventOnlyIn": [],
    "storableIn": [
        "b2w2",
        "bdsp",
        "bw",
        "c",
        "dp",
        "e",
        "frlg",
        "go",
        "gs",
        "hgss",
        "home",
        "lgpe",
        "oras",
        "pt",
        "rb",
        "rs",
        "sm",
        "swsh",
        "usum",
        "xy",
        "y"
    ],
    "shinyReleased": true,
    "shinyBase": null,
    "baseStats": {
        "hp": 90,
        "atk": 85,
        "def": 100,
        "spa": 95,
        "spd": 125,
        "spe": 85
    },
    "goStats": {
        "atk": 192,
        "def": 236,
        "sta": 207
    },
    "weight": {
        "avg": 55.4,
        "min": -1,
        "max": -1,
        "alpha": -1
    },
    "height": {
        "avg": 1.7,
        "min": -1,
        "max": -1,
        "alpha": -1
    },
    "maleRate": -1,
    "femaleRate": -1,
    "refs": {
        "pogo": "ARTICUNO",
        "veekunDb": "articuno",
        "serebii": "articuno",
        "bulbapedia": "Articuno",
        "homeSprite": "articuno",
        "miniSprite": "articuno",
        "showdown": "articuno",
        "showdownDef": "Articuno",
        "smogon": "articuno"
    },
    "imgs": {
        "home": "0144",
        "menu": "0144"
    },
    "baseSpecies": null,
    "baseForms": [],
    "forms": [
        "articuno",
        "articuno-galar"
    ],
    "evolutions": []
}
