{
    "id": "bounsweet",
    "nid": "0761",
    "dexNum": 761,
    "formId": null,
    "name": "Bounsweet",
    "formName": null,
    "region": "alola",
    "generation": 7,
    "type1": "grass",
    "type2": null,
    "color": "purple",
    "abilities": {
        "primary": "Leaf Guard",
        "secondary": "Oblivious",
        "hidden": "Sweet Veil"
    },
    "isLegendary": false,
    "isMythical": false,
    "isUltraBeast": false,
    "ultraBeastCode": null,
    "isDefault": true,
    "isForm": false,
    "isSpecialAbilityForm": false,
    "isCosmeticForm": false,
    "isFemaleForm": false,
    "hasGenderDifferences": false,
    "isBattleOnlyForm": false,
    "isSwitchableForm": false,
    "isFusion": false,
    "fusedWith": null,
    "isMega": false,
    "isPrimal": false,
    "isRegional": false,
    "isGmax": false,
    "canGmax": false,
    "canDynamax": true,
    "canBeAlpha": false,
    "debutIn": "sm",
    "obtainableIn": [
        "sm",
        "sv",
        "swsh",
        "usum"
    ],
    "versionExclusiveIn": [],
    "eventOnlyIn": [],
    "storableIn": [
        "home",
        "sm",
        "sv",
        "swsh",
        "usum"
    ],
    "shinyReleased": true,
    "shinyBase": null,
    "baseStats": {
        "hp": 42,
        "atk": 30,
        "def": 38,
        "spa": 30,
        "spd": 38,
        "spe": 32
    },
    "goStats": {
        "atk": 55,
        "def": 69,
        "sta": 123
    },
    "weight": {
        "avg": 3.2,
        "min": -1,
        "max": -1,
        "alpha": -1
    },
    "height": {
        "avg": 0.3,
        "min": -1,
        "max": -1,
        "alpha": -1
    },
    "maleRate": -1,
    "femaleRate": -1,
    "refs": {
        "pogo": "BOUNSWEET",
        "veekunDb": "bounsweet",
        "smogon": "bounsweet",
        "showdown": "bounsweet",
        "showdownDef": "Bounsweet",
        "serebii": "bounsweet",
        "bulbapedia": "Bounsweet",
        "homeSprite": "0761",
        "miniSprite": "0761"
    },
    "baseSpecies": null,
    "baseForms": [],
    "forms": [
        "bounsweet"
    ],
    "evolutions": []
}
