{
    "id": "eiscue",
    "nid": "0875",
    "dexNum": 875,
    "formId": "ice",
    "name": "Eiscue",
    "formName": "Ice Face",
    "region": "galar",
    "generation": 8,
    "type1": "ice",
    "type2": null,
    "color": "blue",
    "abilities": {
        "primary": "Ice Face",
        "secondary": null,
        "hidden": null
    },
    "isLegendary": false,
    "isMythical": false,
    "isUltraBeast": false,
    "ultraBeastCode": null,
    "isDefault": true,
    "isForm": false,
    "isSpecialAbilityForm": false,
    "isCosmeticForm": false,
    "isFemaleForm": false,
    "hasGenderDifferences": false,
    "isBattleOnlyForm": false,
    "isSwitchableForm": false,
    "isFusion": false,
    "fusedWith": null,
    "isMega": false,
    "isPrimal": false,
    "isRegional": false,
    "isGmax": false,
    "canGmax": false,
    "canDynamax": true,
    "canBeAlpha": false,
    "debutIn": "swsh",
    "obtainableIn": [
        "swsh"
    ],
    "versionExclusiveIn": [],
    "eventOnlyIn": [],
    "storableIn": [
        "home",
        "swsh"
    ],
    "shinyReleased": true,
    "shinyBase": null,
    "baseStats": {
        "hp": 75,
        "atk": 80,
        "def": 110,
        "spa": 65,
        "spd": 90,
        "spe": 50
    },
    "goStats": {
        "atk": 148,
        "def": 195,
        "sta": 181
    },
    "weight": {
        "avg": 89,
        "min": -1,
        "max": -1,
        "alpha": -1
    },
    "height": {
        "avg": 1.4,
        "min": -1,
        "max": -1,
        "alpha": -1
    },
    "maleRate": -1,
    "femaleRate": -1,
    "refs": {
        "pogo": "EISCUE",
        "veekunDb": "eiscue",
        "serebii": "eiscue",
        "bulbapedia": "Eiscue",
        "homeSprite": "0875",
        "miniSprite": "0875",
        "showdown": "eiscue",
        "showdownDef": "Eiscue",
        "smogon": "eiscue"
    },
    "baseSpecies": null,
    "baseForms": [],
    "forms": [
        "eiscue",
        "eiscue-noice"
    ],
    "evolutions": []
}
