{
    "id": "golisopod",
    "nid": "0768",
    "dexNum": 768,
    "formId": null,
    "name": "Golisopod",
    "formName": null,
    "region": "alola",
    "generation": 7,
    "type1": "bug",
    "type2": "water",
    "color": "gray",
    "abilities": {
        "primary": "Emergency Exit",
        "secondary": null,
        "hidden": null
    },
    "isLegendary": false,
    "isMythical": false,
    "isUltraBeast": false,
    "ultraBeastCode": null,
    "isDefault": true,
    "isForm": false,
    "isSpecialAbilityForm": false,
    "isCosmeticForm": false,
    "isFemaleForm": false,
    "hasGenderDifferences": false,
    "isBattleOnlyForm": false,
    "isSwitchableForm": false,
    "isFusion": false,
    "fusedWith": null,
    "isMega": false,
    "isPrimal": false,
    "isRegional": false,
    "isGmax": false,
    "canGmax": false,
    "canDynamax": true,
    "canBeAlpha": false,
    "debutIn": "sm",
    "obtainableIn": [
        "sm",
        "swsh",
        "usum"
    ],
    "versionExclusiveIn": [],
    "eventOnlyIn": [],
    "storableIn": [
        "home",
        "sm",
        "swsh",
        "usum"
    ],
    "shinyReleased": true,
    "shinyBase": null,
    "baseStats": {
        "hp": 75,
        "atk": 125,
        "def": 140,
        "spa": 60,
        "spd": 90,
        "spe": 40
    },
    "goStats": {
        "maxCP": -1,
        "attack": -1,
        "defense": -1,
        "stamina": -1
    },
    "weight": {
        "avg": 108,
        "min": -1,
        "max": -1,
        "alpha": -1
    },
    "height": {
        "avg": 2,
        "min": -1,
        "max": -1,
        "alpha": -1
    },
    "maleRate": -1,
    "femaleRate": -1,
    "refs": {
        "pogo": "GOLISOPOD",
        "veekunDb": "golisopod",
        "serebii": "golisopod",
        "bulbapedia": "Golisopod",
        "homeSprite": "golisopod",
        "miniSprite": "golisopod",
        "showdown": "golisopod",
        "showdownDef": "Golisopod",
        "smogon": "golisopod"
    },
    "baseSpecies": null,
    "baseForms": [],
    "forms": [
        "golisopod"
    ],
    "evolutions": []
}
