{
    "id": "incineroar",
    "nid": "0727",
    "dexNum": 727,
    "formId": null,
    "name": "Incineroar",
    "formName": null,
    "region": "alola",
    "generation": 7,
    "type1": "fire",
    "type2": "dark",
    "color": "red",
    "abilities": {
        "primary": "Blaze",
        "secondary": null,
        "hidden": "Intimidate"
    },
    "isLegendary": false,
    "isMythical": false,
    "isUltraBeast": false,
    "ultraBeastCode": null,
    "isDefault": true,
    "isForm": false,
    "isSpecialAbilityForm": false,
    "isCosmeticForm": false,
    "isFemaleForm": false,
    "hasGenderDifferences": false,
    "isBattleOnlyForm": false,
    "isSwitchableForm": false,
    "isFusion": false,
    "fusedWith": null,
    "isMega": false,
    "isPrimal": false,
    "isRegional": false,
    "isGmax": false,
    "canGmax": false,
    "canDynamax": true,
    "canBeAlpha": false,
    "debutIn": "sm",
    "obtainableIn": [
        "go",
        "sm",
        "swsh",
        "usum"
    ],
    "versionExclusiveIn": [],
    "eventOnlyIn": [],
    "storableIn": [
        "go",
        "home",
        "sm",
        "swsh",
        "usum"
    ],
    "shinyReleased": true,
    "shinyBase": null,
    "baseStats": {
        "hp": 95,
        "atk": 115,
        "def": 90,
        "spa": 80,
        "spd": 90,
        "spe": 60
    },
    "goStats": {
        "maxCP": -1,
        "attack": -1,
        "defense": -1,
        "stamina": -1
    },
    "weight": {
        "avg": 83,
        "min": "-1kg",
        "max": "-1kg",
        "alpha": "-1kg"
    },
    "height": {
        "avg": 1.8,
        "min": "-1m",
        "max": "-1m",
        "alpha": "-1m"
    },
    "maleRate": -1,
    "femaleRate": -1,
    "refs": {
        "pogo": "INCINEROAR",
        "veekunDb": "incineroar",
        "serebii": "incineroar",
        "bulbapedia": "Incineroar",
        "homeSprite": "incineroar",
        "miniSprite": "incineroar",
        "showdown": "incineroar",
        "showdownDef": "Incineroar",
        "smogon": "incineroar"
    },
    "baseSpecies": null,
    "baseForms": [],
    "forms": [
        "incineroar"
    ],
    "evolutions": []
}
