{
    "id": "rhyperior",
    "nid": "0464",
    "dexNum": 464,
    "formId": null,
    "name": "Rhyperior",
    "formName": null,
    "region": "sinnoh",
    "generation": 4,
    "type1": "ground",
    "type2": "rock",
    "color": "gray",
    "abilities": {
        "primary": "Lightning Rod",
        "secondary": "Solid Rock",
        "hidden": "Reckless"
    },
    "isLegendary": false,
    "isMythical": false,
    "isUltraBeast": false,
    "ultraBeastCode": null,
    "isDefault": true,
    "isForm": false,
    "isSpecialAbilityForm": false,
    "isCosmeticForm": false,
    "isFemaleForm": false,
    "hasGenderDifferences": true,
    "isBattleOnlyForm": false,
    "isSwitchableForm": false,
    "isFusion": false,
    "fusedWith": null,
    "isMega": false,
    "isPrimal": false,
    "isRegional": false,
    "isGmax": false,
    "canGmax": false,
    "canDynamax": true,
    "canBeAlpha": true,
    "debutIn": "dp",
    "obtainableIn": [
        "bdsp",
        "dp",
        "go",
        "la",
        "pt",
        "swsh"
    ],
    "versionExclusiveIn": [],
    "eventOnlyIn": [],
    "storableIn": [
        "b2w2",
        "bdsp",
        "bw",
        "dp",
        "go",
        "hgss",
        "home",
        "la",
        "oras",
        "pt",
        "sm",
        "swsh",
        "usum",
        "xy"
    ],
    "shinyReleased": true,
    "shinyBase": null,
    "baseStats": {
        "hp": 115,
        "atk": 140,
        "def": 130,
        "spa": 55,
        "spd": 55,
        "spe": 40
    },
    "goStats": {
        "atk": 241,
        "def": 190,
        "sta": 251
    },
    "weight": {
        "avg": 282.8,
        "min": -1,
        "max": -1,
        "alpha": -1
    },
    "height": {
        "avg": 2.4,
        "min": -1,
        "max": -1,
        "alpha": -1
    },
    "maleRate": -1,
    "femaleRate": -1,
    "refs": {
        "pogo": "RHYPERIOR",
        "veekunDb": "rhyperior",
        "serebii": "rhyperior",
        "bulbapedia": "Rhyperior",
        "homeSprite": "0464",
        "miniSprite": "0464",
        "showdown": "rhyperior",
        "showdownDef": "Rhyperior",
        "smogon": "rhyperior"
    },
    "baseSpecies": null,
    "baseForms": [],
    "forms": [
        "rhyperior",
        "rhyperior-f"
    ],
    "evolutions": [],
    "imgs": {
        "home": "0464",
        "menu": "0464"
    }
}
