{
    "id": "steenee",
    "nid": "0762",
    "dexNum": 762,
    "formId": null,
    "name": "Steenee",
    "formName": null,
    "region": "alola",
    "generation": 7,
    "type1": "grass",
    "type2": null,
    "color": "purple",
    "abilities": {
        "primary": "Leaf Guard",
        "secondary": "Oblivious",
        "hidden": "Sweet Veil"
    },
    "isLegendary": false,
    "isMythical": false,
    "isUltraBeast": false,
    "ultraBeastCode": null,
    "isDefault": true,
    "isForm": false,
    "isSpecialAbilityForm": false,
    "isCosmeticForm": false,
    "isFemaleForm": false,
    "hasGenderDifferences": false,
    "isBattleOnlyForm": false,
    "isSwitchableForm": false,
    "isFusion": false,
    "fusedWith": null,
    "isMega": false,
    "isPrimal": false,
    "isRegional": false,
    "isGmax": false,
    "canGmax": false,
    "canDynamax": true,
    "canBeAlpha": false,
    "debutIn": "sm",
    "obtainableIn": [
        "sm",
        "swsh",
        "usum"
    ],
    "versionExclusiveIn": [],
    "eventOnlyIn": [],
    "storableIn": [
        "home",
        "sm",
        "swsh",
        "usum"
    ],
    "shinyReleased": true,
    "shinyBase": null,
    "baseStats": {
        "hp": 52,
        "atk": 40,
        "def": 48,
        "spa": 40,
        "spd": 48,
        "spe": 62
    },
    "goStats": {
        "atk": 78,
        "def": 94,
        "sta": 141
    },
    "weight": {
        "avg": 8.2,
        "min": -1,
        "max": -1,
        "alpha": -1
    },
    "height": {
        "avg": 0.7,
        "min": -1,
        "max": -1,
        "alpha": -1
    },
    "maleRate": -1,
    "femaleRate": -1,
    "refs": {
        "pogo": "STEENEE",
        "veekunDb": "steenee",
        "serebii": "steenee",
        "bulbapedia": "Steenee",
        "homeSprite": "0762",
        "miniSprite": "0762",
        "showdown": "steenee",
        "showdownDef": "Steenee",
        "smogon": "steenee"
    },
    "baseSpecies": null,
    "baseForms": [],
    "forms": [
        "steenee"
    ],
    "evolutions": [],
    "imgs": {
        "home": "0762",
        "menu": "0762"
    }
}
