{
    "id": "steelix",
    "nid": "0208",
    "dexNum": 208,
    "formId": null,
    "name": "Steelix",
    "formName": null,
    "region": "johto",
    "generation": 2,
    "type1": "steel",
    "type2": "ground",
    "color": "gray",
    "abilities": {
        "primary": "Rock Head",
        "secondary": "Sturdy",
        "hidden": "Sheer Force"
    },
    "isLegendary": false,
    "isMythical": false,
    "isUltraBeast": false,
    "ultraBeastCode": null,
    "isDefault": true,
    "isForm": false,
    "isSpecialAbilityForm": false,
    "isCosmeticForm": false,
    "isFemaleForm": false,
    "hasGenderDifferences": true,
    "isBattleOnlyForm": false,
    "isSwitchableForm": false,
    "isFusion": false,
    "fusedWith": null,
    "isMega": false,
    "isPrimal": false,
    "isRegional": false,
    "isGmax": false,
    "canGmax": false,
    "canDynamax": true,
    "canBeAlpha": true,
    "debutIn": "gs",
    "obtainableIn": [
        "bdsp",
        "c",
        "go",
        "gs",
        "hgss",
        "la",
        "swsh"
    ],
    "versionExclusiveIn": [],
    "eventOnlyIn": [],
    "storableIn": [
        "b2w2",
        "bdsp",
        "bw",
        "c",
        "dp",
        "e",
        "frlg",
        "go",
        "gs",
        "hgss",
        "home",
        "la",
        "oras",
        "pt",
        "rs",
        "sm",
        "swsh",
        "usum",
        "xy"
    ],
    "shinyReleased": true,
    "shinyBase": null,
    "baseStats": {
        "hp": 75,
        "atk": 85,
        "def": 200,
        "spa": 55,
        "spd": 65,
        "spe": 30
    },
    "goStats": {
        "maxCP": -1,
        "attack": -1,
        "defense": -1,
        "stamina": -1
    },
    "weight": {
        "avg": 400,
        "min": -1,
        "max": -1,
        "alpha": -1
    },
    "height": {
        "avg": 9.2,
        "min": -1,
        "max": -1,
        "alpha": -1
    },
    "maleRate": -1,
    "femaleRate": -1,
    "refs": {
        "pogo": "STEELIX",
        "veekunDb": "steelix",
        "serebii": "steelix",
        "bulbapedia": "Steelix",
        "homeSprite": "steelix",
        "miniSprite": "steelix",
        "showdown": "steelix",
        "showdownDef": "Steelix",
        "smogon": "steelix"
    },
    "baseSpecies": null,
    "baseForms": [],
    "forms": [
        "steelix",
        "steelix-f",
        "steelix-mega"
    ],
    "evolutions": []
}
