{
    "id": "tirtouga",
    "nid": "0564",
    "dexNum": 564,
    "formId": null,
    "name": "Tirtouga",
    "formName": null,
    "region": "unova",
    "generation": 5,
    "type1": "water",
    "type2": "rock",
    "color": "blue",
    "abilities": {
        "primary": "Solid Rock",
        "secondary": "Sturdy",
        "hidden": "Swift Swim"
    },
    "isLegendary": false,
    "isMythical": false,
    "isUltraBeast": false,
    "ultraBeastCode": null,
    "isDefault": true,
    "isForm": false,
    "isSpecialAbilityForm": false,
    "isCosmeticForm": false,
    "isFemaleForm": false,
    "hasGenderDifferences": false,
    "isBattleOnlyForm": false,
    "isSwitchableForm": false,
    "isFusion": false,
    "fusedWith": null,
    "isMega": false,
    "isPrimal": false,
    "isRegional": false,
    "isGmax": false,
    "canGmax": false,
    "canDynamax": true,
    "canBeAlpha": false,
    "debutIn": "bw",
    "obtainableIn": [
        "b2w2",
        "bw",
        "go",
        "swsh"
    ],
    "versionExclusiveIn": [],
    "eventOnlyIn": [],
    "storableIn": [
        "b2w2",
        "bw",
        "go",
        "home",
        "oras",
        "sm",
        "swsh",
        "usum",
        "xy"
    ],
    "shinyReleased": true,
    "shinyBase": null,
    "baseStats": {
        "hp": 54,
        "atk": 78,
        "def": 103,
        "spa": 53,
        "spd": 45,
        "spe": 22
    },
    "goStats": {
        "maxCP": -1,
        "attack": -1,
        "defense": -1,
        "stamina": -1
    },
    "weight": {
        "avg": 16.5,
        "min": "-1kg",
        "max": "-1kg",
        "alpha": "-1kg"
    },
    "height": {
        "avg": 0.7,
        "min": "-1m",
        "max": "-1m",
        "alpha": "-1m"
    },
    "maleRate": -1,
    "femaleRate": -1,
    "refs": {
        "pogo": "TIRTOUGA",
        "veekunDb": "tirtouga",
        "serebii": "tirtouga",
        "bulbapedia": "Tirtouga",
        "homeSprite": "tirtouga",
        "miniSprite": "tirtouga",
        "showdown": "tirtouga",
        "showdownDef": "Tirtouga",
        "smogon": "tirtouga"
    },
    "baseSpecies": null,
    "baseForms": [],
    "forms": [
        "tirtouga"
    ],
    "evolutions": []
}
