{
    "id": "tornadus",
    "nid": "0641",
    "dexNum": 641,
    "formId": "incarnate",
    "name": "Tornadus",
    "formName": "Incarnate Forme",
    "region": "unova",
    "generation": 5,
    "type1": "flying",
    "type2": null,
    "color": "green",
    "abilities": {
        "primary": "Prankster",
        "secondary": null,
        "hidden": "Defiant"
    },
    "isLegendary": true,
    "isMythical": false,
    "isUltraBeast": false,
    "ultraBeastCode": null,
    "isDefault": true,
    "isForm": false,
    "isSpecialAbilityForm": false,
    "isCosmeticForm": false,
    "isFemaleForm": false,
    "hasGenderDifferences": false,
    "isBattleOnlyForm": false,
    "isSwitchableForm": false,
    "isFusion": false,
    "fusedWith": null,
    "isMega": false,
    "isPrimal": false,
    "isRegional": false,
    "isGmax": false,
    "canGmax": false,
    "canDynamax": true,
    "canBeAlpha": false,
    "debutIn": "bw",
    "obtainableIn": [
        "b2w2",
        "bw",
        "go",
        "la",
        "swsh"
    ],
    "versionExclusiveIn": [],
    "eventOnlyIn": [],
    "storableIn": [
        "b2w2",
        "bw",
        "go",
        "home",
        "la",
        "oras",
        "sm",
        "swsh",
        "usum",
        "xy"
    ],
    "shinyReleased": true,
    "shinyBase": null,
    "baseStats": {
        "hp": 79,
        "atk": 115,
        "def": 70,
        "spa": 125,
        "spd": 80,
        "spe": 111
    },
    "goStats": {
        "maxCP": -1,
        "attack": -1,
        "defense": -1,
        "stamina": -1
    },
    "weight": {
        "avg": 63,
        "min": "-1kg",
        "max": "-1kg",
        "alpha": "-1kg"
    },
    "height": {
        "avg": 1.5,
        "min": "-1m",
        "max": "-1m",
        "alpha": "-1m"
    },
    "maleRate": -1,
    "femaleRate": -1,
    "refs": {
        "pogo": "TORNADUS",
        "veekunDb": "tornadus",
        "serebii": "tornadus",
        "bulbapedia": "Tornadus",
        "homeSprite": "tornadus",
        "miniSprite": "tornadus",
        "showdown": "tornadus",
        "showdownDef": "Tornadus",
        "smogon": "tornadus"
    },
    "baseSpecies": null,
    "baseForms": [],
    "forms": [
        "tornadus",
        "tornadus-therian"
    ],
    "evolutions": []
}
